<?xml version="1.0" encoding="UTF-8"?><?xml-stylesheet type="text/xsl" href="report.xsl"?><swebserv>
  <date>Wed Aug 07 23:13:03 CDT 2013</date>
  <meanReqServiceRate>10.21</meanReqServiceRate>
  <maxReqQueueLength>200</maxReqQueueLength>
  <nReq>10000</nReq>
  <PRNGseed>142857</PRNGseed>
  <meanWaitTimeVsX>C:\results\meanWaitTimeVsX.png</meanWaitTimeVsX>
  <dropFractionVsX>C:\results\dropFractionVsX.png</dropFractionVsX>
  <simulations>
    <simulation meanReqArrivalRate="1.0" meanWaitTime="0.10696776761105119" reqDropFraction="0.0" waitTimeStddev="0.10766049577374925"/>
    <simulation meanReqArrivalRate="1.1" meanWaitTime="0.10945945753169646" reqDropFraction="0.0" waitTimeStddev="0.11043201142768092"/>
    <simulation meanReqArrivalRate="1.2" meanWaitTime="0.11079974424302474" reqDropFraction="0.0" waitTimeStddev="0.11080019357820176"/>
    <simulation meanReqArrivalRate="1.3" meanWaitTime="0.11285753115857683" reqDropFraction="0.0" waitTimeStddev="0.1145155645732351"/>
    <simulation meanReqArrivalRate="1.4" meanWaitTime="0.11491073736440208" reqDropFraction="0.0" waitTimeStddev="0.11411344787044189"/>
    <simulation meanReqArrivalRate="1.5" meanWaitTime="0.1163582132224694" reqDropFraction="0.0" waitTimeStddev="0.11695812044822615"/>
    <simulation meanReqArrivalRate="1.6" meanWaitTime="0.11410124202868756" reqDropFraction="0.0" waitTimeStddev="0.11285726602285905"/>
    <simulation meanReqArrivalRate="1.7000000000000002" meanWaitTime="0.11795505225282359" reqDropFraction="0.0" waitTimeStddev="0.11654294541078761"/>
    <simulation meanReqArrivalRate="1.8" meanWaitTime="0.11819894791105971" reqDropFraction="0.0" waitTimeStddev="0.1183367657259931"/>
    <simulation meanReqArrivalRate="1.9" meanWaitTime="0.1201553011656646" reqDropFraction="0.0" waitTimeStddev="0.11842382331351228"/>
    <simulation meanReqArrivalRate="2.0" meanWaitTime="0.12150151097364507" reqDropFraction="0.0" waitTimeStddev="0.11893956644530569"/>
    <simulation meanReqArrivalRate="2.1" meanWaitTime="0.12449197250487018" reqDropFraction="0.0" waitTimeStddev="0.1229943490739014"/>
    <simulation meanReqArrivalRate="2.2" meanWaitTime="0.1259617274540434" reqDropFraction="0.0" waitTimeStddev="0.12492760158458639"/>
    <simulation meanReqArrivalRate="2.3" meanWaitTime="0.1314882310058494" reqDropFraction="0.0" waitTimeStddev="0.13163857394020972"/>
    <simulation meanReqArrivalRate="2.4000000000000004" meanWaitTime="0.1294168232023565" reqDropFraction="0.0" waitTimeStddev="0.12985243120801693"/>
    <simulation meanReqArrivalRate="2.5" meanWaitTime="0.13064320697543821" reqDropFraction="0.0" waitTimeStddev="0.13295441359099963"/>
    <simulation meanReqArrivalRate="2.6" meanWaitTime="0.13015278224345583" reqDropFraction="0.0" waitTimeStddev="0.13145885755757458"/>
    <simulation meanReqArrivalRate="2.7" meanWaitTime="0.13386788315397494" reqDropFraction="0.0" waitTimeStddev="0.13366366975859842"/>
    <simulation meanReqArrivalRate="2.8" meanWaitTime="0.13486513048153395" reqDropFraction="0.0" waitTimeStddev="0.1367702517394872"/>
    <simulation meanReqArrivalRate="2.9000000000000004" meanWaitTime="0.13950409524479115" reqDropFraction="0.0" waitTimeStddev="0.14370269322685622"/>
    <simulation meanReqArrivalRate="3.0" meanWaitTime="0.1381088952426614" reqDropFraction="0.0" waitTimeStddev="0.13520148591500727"/>
    <simulation meanReqArrivalRate="3.1" meanWaitTime="0.14334734074942757" reqDropFraction="0.0" waitTimeStddev="0.1471990841844222"/>
    <simulation meanReqArrivalRate="3.2" meanWaitTime="0.14331638760827453" reqDropFraction="0.0" waitTimeStddev="0.14454534770783914"/>
    <simulation meanReqArrivalRate="3.3000000000000003" meanWaitTime="0.14020143028100154" reqDropFraction="0.0" waitTimeStddev="0.1388525755777064"/>
    <simulation meanReqArrivalRate="3.4000000000000004" meanWaitTime="0.14808052915443923" reqDropFraction="0.0" waitTimeStddev="0.1481633122718962"/>
    <simulation meanReqArrivalRate="3.5" meanWaitTime="0.15326798434040445" reqDropFraction="0.0" waitTimeStddev="0.15283202053260755"/>
    <simulation meanReqArrivalRate="3.6" meanWaitTime="0.15337863980215813" reqDropFraction="0.0" waitTimeStddev="0.15638158450774006"/>
    <simulation meanReqArrivalRate="3.7" meanWaitTime="0.15181895873042547" reqDropFraction="0.0" waitTimeStddev="0.15005272781565815"/>
    <simulation meanReqArrivalRate="3.8000000000000003" meanWaitTime="0.1558307817387573" reqDropFraction="0.0" waitTimeStddev="0.15387307196016473"/>
    <simulation meanReqArrivalRate="3.9000000000000004" meanWaitTime="0.15712451203816344" reqDropFraction="0.0" waitTimeStddev="0.15202525687604054"/>
    <simulation meanReqArrivalRate="4.0" meanWaitTime="0.16424139968929963" reqDropFraction="0.0" waitTimeStddev="0.16216099423303848"/>
    <simulation meanReqArrivalRate="4.1" meanWaitTime="0.16884122412140587" reqDropFraction="0.0" waitTimeStddev="0.1835817136436626"/>
    <simulation meanReqArrivalRate="4.2" meanWaitTime="0.1639246001119989" reqDropFraction="0.0" waitTimeStddev="0.16806294133133126"/>
    <simulation meanReqArrivalRate="4.300000000000001" meanWaitTime="0.17227757145745323" reqDropFraction="0.0" waitTimeStddev="0.17285198270754806"/>
    <simulation meanReqArrivalRate="4.4" meanWaitTime="0.1802230663180272" reqDropFraction="0.0" waitTimeStddev="0.1828444343731082"/>
    <simulation meanReqArrivalRate="4.5" meanWaitTime="0.17250895081864456" reqDropFraction="0.0" waitTimeStddev="0.1778281962243677"/>
    <simulation meanReqArrivalRate="4.6" meanWaitTime="0.17269635780705583" reqDropFraction="0.0" waitTimeStddev="0.17085051406648089"/>
    <simulation meanReqArrivalRate="4.7" meanWaitTime="0.182917802523827" reqDropFraction="0.0" waitTimeStddev="0.18447879534325537"/>
    <simulation meanReqArrivalRate="4.800000000000001" meanWaitTime="0.18248469915377208" reqDropFraction="0.0" waitTimeStddev="0.18123637398941905"/>
    <simulation meanReqArrivalRate="4.9" meanWaitTime="0.17946601072799248" reqDropFraction="0.0" waitTimeStddev="0.17398126016613796"/>
    <simulation meanReqArrivalRate="5.0" meanWaitTime="0.19503069208660626" reqDropFraction="0.0" waitTimeStddev="0.1985627006503516"/>
    <simulation meanReqArrivalRate="5.1000000000000005" meanWaitTime="0.18840768657271126" reqDropFraction="0.0" waitTimeStddev="0.18370078317701755"/>
    <simulation meanReqArrivalRate="5.2" meanWaitTime="0.20045615710400397" reqDropFraction="0.0" waitTimeStddev="0.199517903558956"/>
    <simulation meanReqArrivalRate="5.3" meanWaitTime="0.1985737974379342" reqDropFraction="0.0" waitTimeStddev="0.19102786328391194"/>
    <simulation meanReqArrivalRate="5.4" meanWaitTime="0.21595344729184304" reqDropFraction="0.0" waitTimeStddev="0.23122403296718044"/>
    <simulation meanReqArrivalRate="5.5" meanWaitTime="0.21497509073842774" reqDropFraction="0.0" waitTimeStddev="0.23133233489343794"/>
    <simulation meanReqArrivalRate="5.6000000000000005" meanWaitTime="0.21570381729382804" reqDropFraction="0.0" waitTimeStddev="0.2148114476285603"/>
    <simulation meanReqArrivalRate="5.7" meanWaitTime="0.21754120108870875" reqDropFraction="0.0" waitTimeStddev="0.217447018003464"/>
    <simulation meanReqArrivalRate="5.800000000000001" meanWaitTime="0.24247612201310922" reqDropFraction="0.0" waitTimeStddev="0.2580666167619015"/>
    <simulation meanReqArrivalRate="5.9" meanWaitTime="0.23036521490038359" reqDropFraction="0.0" waitTimeStddev="0.23370555582776065"/>
    <simulation meanReqArrivalRate="6.0" meanWaitTime="0.2325839308820427" reqDropFraction="0.0" waitTimeStddev="0.22243969546948858"/>
    <simulation meanReqArrivalRate="6.1000000000000005" meanWaitTime="0.24584514951434752" reqDropFraction="0.0" waitTimeStddev="0.24951719559254856"/>
    <simulation meanReqArrivalRate="6.2" meanWaitTime="0.271438720964189" reqDropFraction="0.0" waitTimeStddev="0.276774173975494"/>
    <simulation meanReqArrivalRate="6.300000000000001" meanWaitTime="0.25028715180587385" reqDropFraction="0.0" waitTimeStddev="0.23574298306402006"/>
    <simulation meanReqArrivalRate="6.4" meanWaitTime="0.26067954812612587" reqDropFraction="0.0" waitTimeStddev="0.2499563243767242"/>
    <simulation meanReqArrivalRate="6.5" meanWaitTime="0.2536025930424079" reqDropFraction="0.0" waitTimeStddev="0.2416515617537861"/>
    <simulation meanReqArrivalRate="6.6000000000000005" meanWaitTime="0.2707820717707847" reqDropFraction="0.0" waitTimeStddev="0.2616506228035536"/>
    <simulation meanReqArrivalRate="6.7" meanWaitTime="0.27352732680997804" reqDropFraction="0.0" waitTimeStddev="0.2725090962839997"/>
    <simulation meanReqArrivalRate="6.800000000000001" meanWaitTime="0.2988448517934651" reqDropFraction="0.0" waitTimeStddev="0.2807757184020217"/>
    <simulation meanReqArrivalRate="6.9" meanWaitTime="0.297751399199054" reqDropFraction="0.0" waitTimeStddev="0.29064972538332556"/>
    <simulation meanReqArrivalRate="7.0" meanWaitTime="0.30570563711214765" reqDropFraction="0.0" waitTimeStddev="0.3143379395537792"/>
    <simulation meanReqArrivalRate="7.1000000000000005" meanWaitTime="0.3468348443291665" reqDropFraction="0.0" waitTimeStddev="0.3703371475926045"/>
    <simulation meanReqArrivalRate="7.2" meanWaitTime="0.34140053733752257" reqDropFraction="0.0" waitTimeStddev="0.334419615427169"/>
    <simulation meanReqArrivalRate="7.300000000000001" meanWaitTime="0.33931227227169736" reqDropFraction="0.0" waitTimeStddev="0.3572221931254939"/>
    <simulation meanReqArrivalRate="7.4" meanWaitTime="0.34595472082808365" reqDropFraction="0.0" waitTimeStddev="0.32295048695085904"/>
    <simulation meanReqArrivalRate="7.5" meanWaitTime="0.377611866862613" reqDropFraction="0.0" waitTimeStddev="0.36277537207431565"/>
    <simulation meanReqArrivalRate="7.6000000000000005" meanWaitTime="0.3651181336977471" reqDropFraction="0.0" waitTimeStddev="0.36526773083758307"/>
    <simulation meanReqArrivalRate="7.7" meanWaitTime="0.4136548881632971" reqDropFraction="0.0" waitTimeStddev="0.4002021064442849"/>
    <simulation meanReqArrivalRate="7.800000000000001" meanWaitTime="0.4266139828248686" reqDropFraction="0.0" waitTimeStddev="0.4195722816107407"/>
    <simulation meanReqArrivalRate="7.9" meanWaitTime="0.47015125781438216" reqDropFraction="0.0" waitTimeStddev="0.544736786988762"/>
    <simulation meanReqArrivalRate="8.0" meanWaitTime="0.41113245060145837" reqDropFraction="0.0" waitTimeStddev="0.4263478588437407"/>
    <simulation meanReqArrivalRate="8.100000000000001" meanWaitTime="0.47389008983064324" reqDropFraction="0.0" waitTimeStddev="0.48412108883200766"/>
    <simulation meanReqArrivalRate="8.2" meanWaitTime="0.603987693637748" reqDropFraction="0.0" waitTimeStddev="0.6123622368537577"/>
    <simulation meanReqArrivalRate="8.3" meanWaitTime="0.47162429156742947" reqDropFraction="0.0" waitTimeStddev="0.4416840912211816"/>
    <simulation meanReqArrivalRate="8.4" meanWaitTime="0.5623749750599836" reqDropFraction="0.0" waitTimeStddev="0.5395743988752715"/>
    <simulation meanReqArrivalRate="8.5" meanWaitTime="0.6075237114127825" reqDropFraction="0.0" waitTimeStddev="0.5313128427750505"/>
    <simulation meanReqArrivalRate="8.600000000000001" meanWaitTime="0.6101031774512387" reqDropFraction="0.0" waitTimeStddev="0.6162080019062779"/>
    <simulation meanReqArrivalRate="8.7" meanWaitTime="0.6729709516508692" reqDropFraction="0.0" waitTimeStddev="0.7065830364021038"/>
    <simulation meanReqArrivalRate="8.8" meanWaitTime="0.6804069539202765" reqDropFraction="0.0" waitTimeStddev="0.5872384269078991"/>
    <simulation meanReqArrivalRate="8.9" meanWaitTime="0.6056405552432369" reqDropFraction="0.0" waitTimeStddev="0.5063628537995956"/>
    <simulation meanReqArrivalRate="9.0" meanWaitTime="0.7892285270311669" reqDropFraction="0.0" waitTimeStddev="0.7905251606266586"/>
    <simulation meanReqArrivalRate="9.1" meanWaitTime="0.9817896366155795" reqDropFraction="0.0" waitTimeStddev="0.9826828724460774"/>
    <simulation meanReqArrivalRate="9.200000000000001" meanWaitTime="1.80354909630551" reqDropFraction="0.0" waitTimeStddev="2.2849110767899834"/>
    <simulation meanReqArrivalRate="9.3" meanWaitTime="1.284809854658494" reqDropFraction="0.0" waitTimeStddev="1.3850479248446539"/>
    <simulation meanReqArrivalRate="9.4" meanWaitTime="1.221958332219033" reqDropFraction="0.0" waitTimeStddev="1.0436489675276184"/>
    <simulation meanReqArrivalRate="9.5" meanWaitTime="1.2250657947968007" reqDropFraction="0.0" waitTimeStddev="0.9741930696786986"/>
    <simulation meanReqArrivalRate="9.6" meanWaitTime="3.04394035869116" reqDropFraction="0.0" waitTimeStddev="3.2002867518965776"/>
    <simulation meanReqArrivalRate="9.700000000000001" meanWaitTime="2.320501459329773" reqDropFraction="0.0" waitTimeStddev="2.3704158582598107"/>
    <simulation meanReqArrivalRate="9.8" meanWaitTime="1.585520482066102" reqDropFraction="0.0" waitTimeStddev="1.3282592414965058"/>
    <simulation meanReqArrivalRate="9.9" meanWaitTime="4.456982016376785" reqDropFraction="0.0" waitTimeStddev="4.266098665427164"/>
    <simulation meanReqArrivalRate="10.0" meanWaitTime="3.5608159869704914" reqDropFraction="0.0" waitTimeStddev="3.486957910052189"/>
    <simulation meanReqArrivalRate="10.1" meanWaitTime="2.2477052638652952" reqDropFraction="0.0" waitTimeStddev="1.8401107573033677"/>
    <simulation meanReqArrivalRate="10.200000000000001" meanWaitTime="2.1411616364109736" reqDropFraction="0.0" waitTimeStddev="1.618302316140086"/>
    <simulation meanReqArrivalRate="10.3" meanWaitTime="8.458823612055644" reqDropFraction="0.0" waitTimeStddev="3.9387893164542653"/>
    <simulation meanReqArrivalRate="10.4" meanWaitTime="15.533921041857115" reqDropFraction="0.0253" waitTimeStddev="4.269428791329076"/>
    <simulation meanReqArrivalRate="10.5" meanWaitTime="10.74514229985242" reqDropFraction="0.0187" waitTimeStddev="6.55227087890333"/>
    <simulation meanReqArrivalRate="10.600000000000001" meanWaitTime="15.298642230514513" reqDropFraction="0.0271" waitTimeStddev="4.3809701096368245"/>
    <simulation meanReqArrivalRate="10.700000000000001" meanWaitTime="14.830473176578371" reqDropFraction="0.0191" waitTimeStddev="4.703424836905513"/>
    <simulation meanReqArrivalRate="10.8" meanWaitTime="14.866338021842985" reqDropFraction="0.0481" waitTimeStddev="6.227574876675341"/>
    <simulation meanReqArrivalRate="10.9" meanWaitTime="14.775669886096791" reqDropFraction="0.0401" waitTimeStddev="6.121584082711045"/>
    <simulation meanReqArrivalRate="11.0" meanWaitTime="16.194882490175836" reqDropFraction="0.0466" waitTimeStddev="4.55353005188615"/>
    <simulation meanReqArrivalRate="11.100000000000001" meanWaitTime="16.85056849773933" reqDropFraction="0.0624" waitTimeStddev="4.30167200208675"/>
    <simulation meanReqArrivalRate="11.200000000000001" meanWaitTime="17.51792159296511" reqDropFraction="0.087" waitTimeStddev="4.180331092045735"/>
    <simulation meanReqArrivalRate="11.3" meanWaitTime="15.809110036875216" reqDropFraction="0.0698" waitTimeStddev="5.2681566311501165"/>
    <simulation meanReqArrivalRate="11.4" meanWaitTime="16.96117278714274" reqDropFraction="0.0824" waitTimeStddev="4.736731365856834"/>
    <simulation meanReqArrivalRate="11.5" meanWaitTime="17.510840622557293" reqDropFraction="0.0882" waitTimeStddev="4.165294919471687"/>
    <simulation meanReqArrivalRate="11.600000000000001" meanWaitTime="17.030033015314917" reqDropFraction="0.1058" waitTimeStddev="4.57925497715736"/>
    <simulation meanReqArrivalRate="11.700000000000001" meanWaitTime="17.76955523870557" reqDropFraction="0.1271" waitTimeStddev="3.7647008572396454"/>
    <simulation meanReqArrivalRate="11.8" meanWaitTime="17.265991911379277" reqDropFraction="0.1141" waitTimeStddev="4.105711696534136"/>
    <simulation meanReqArrivalRate="11.9" meanWaitTime="17.25065833940507" reqDropFraction="0.1104" waitTimeStddev="4.79027314966954"/>
    <simulation meanReqArrivalRate="12.0" meanWaitTime="17.228227310610592" reqDropFraction="0.1204" waitTimeStddev="4.995382321465602"/>
    <simulation meanReqArrivalRate="12.100000000000001" meanWaitTime="18.375552209843114" reqDropFraction="0.1509" waitTimeStddev="3.8852230727014283"/>
    <simulation meanReqArrivalRate="12.200000000000001" meanWaitTime="17.094746041327124" reqDropFraction="0.1356" waitTimeStddev="5.12801725224745"/>
    <simulation meanReqArrivalRate="12.3" meanWaitTime="18.211619286290677" reqDropFraction="0.1842" waitTimeStddev="4.591956568179193"/>
    <simulation meanReqArrivalRate="12.4" meanWaitTime="17.912079073703545" reqDropFraction="0.1506" waitTimeStddev="3.892869977506686"/>
    <simulation meanReqArrivalRate="12.5" meanWaitTime="17.728469827350327" reqDropFraction="0.1504" waitTimeStddev="3.692973776577011"/>
    <simulation meanReqArrivalRate="12.600000000000001" meanWaitTime="18.522667643113724" reqDropFraction="0.1809" waitTimeStddev="3.4238110427179222"/>
    <simulation meanReqArrivalRate="12.700000000000001" meanWaitTime="18.288531772074947" reqDropFraction="0.1899" waitTimeStddev="4.070247574506841"/>
    <simulation meanReqArrivalRate="12.8" meanWaitTime="18.264791057950568" reqDropFraction="0.1815" waitTimeStddev="3.5485747984326665"/>
    <simulation meanReqArrivalRate="12.9" meanWaitTime="18.387806644632867" reqDropFraction="0.1792" waitTimeStddev="2.811256082035281"/>
    <simulation meanReqArrivalRate="13.0" meanWaitTime="17.429391683261887" reqDropFraction="0.1745" waitTimeStddev="4.038532149476705"/>
    <simulation meanReqArrivalRate="13.100000000000001" meanWaitTime="18.04447708666116" reqDropFraction="0.2082" waitTimeStddev="3.8819281914198003"/>
    <simulation meanReqArrivalRate="13.200000000000001" meanWaitTime="18.75399589448661" reqDropFraction="0.2277" waitTimeStddev="3.354129386055294"/>
    <simulation meanReqArrivalRate="13.3" meanWaitTime="18.07158427100557" reqDropFraction="0.202" waitTimeStddev="3.6832691256748147"/>
    <simulation meanReqArrivalRate="13.4" meanWaitTime="18.305958780682047" reqDropFraction="0.2087" waitTimeStddev="3.2172086120551393"/>
    <simulation meanReqArrivalRate="13.5" meanWaitTime="18.551769071988513" reqDropFraction="0.2414" waitTimeStddev="3.9538251417965706"/>
    <simulation meanReqArrivalRate="13.600000000000001" meanWaitTime="18.254269261024362" reqDropFraction="0.2388" waitTimeStddev="4.049866192541184"/>
    <simulation meanReqArrivalRate="13.700000000000001" meanWaitTime="17.980460837571382" reqDropFraction="0.2263" waitTimeStddev="4.34621976876705"/>
    <simulation meanReqArrivalRate="13.8" meanWaitTime="17.90746383813542" reqDropFraction="0.2301" waitTimeStddev="3.8670558661112087"/>
    <simulation meanReqArrivalRate="13.9" meanWaitTime="18.463940733641994" reqDropFraction="0.2461" waitTimeStddev="3.7356232339928126"/>
    <simulation meanReqArrivalRate="14.0" meanWaitTime="18.37619359295055" reqDropFraction="0.2401" waitTimeStddev="3.4543901533279597"/>
    <simulation meanReqArrivalRate="14.100000000000001" meanWaitTime="18.237929423578052" reqDropFraction="0.2531" waitTimeStddev="3.6329365662617223"/>
    <simulation meanReqArrivalRate="14.200000000000001" meanWaitTime="18.45469434853727" reqDropFraction="0.2672" waitTimeStddev="3.496500893425737"/>
    <simulation meanReqArrivalRate="14.3" meanWaitTime="18.648739091376765" reqDropFraction="0.2687" waitTimeStddev="3.3417619704735295"/>
    <simulation meanReqArrivalRate="14.4" meanWaitTime="18.181561475956556" reqDropFraction="0.2575" waitTimeStddev="3.3962738715938254"/>
    <simulation meanReqArrivalRate="14.5" meanWaitTime="18.418146991694396" reqDropFraction="0.2654" waitTimeStddev="3.297478772107558"/>
    <simulation meanReqArrivalRate="14.600000000000001" meanWaitTime="18.68021681856421" reqDropFraction="0.2833" waitTimeStddev="3.145860416969705"/>
    <simulation meanReqArrivalRate="14.700000000000001" meanWaitTime="18.326012428893737" reqDropFraction="0.2916" waitTimeStddev="3.993859091592554"/>
    <simulation meanReqArrivalRate="14.8" meanWaitTime="18.3724653740375" reqDropFraction="0.291" waitTimeStddev="3.4640710817298874"/>
    <simulation meanReqArrivalRate="14.9" meanWaitTime="18.378240046438716" reqDropFraction="0.287" waitTimeStddev="2.9173901618452134"/>
    <simulation meanReqArrivalRate="15.0" meanWaitTime="18.716667953540323" reqDropFraction="0.2916" waitTimeStddev="3.1465340098110324"/>
    <simulation meanReqArrivalRate="15.100000000000001" meanWaitTime="18.72252670928227" reqDropFraction="0.314" waitTimeStddev="3.372733771790372"/>
    <simulation meanReqArrivalRate="15.200000000000001" meanWaitTime="18.658506441193445" reqDropFraction="0.2994" waitTimeStddev="3.1501630865406787"/>
    <simulation meanReqArrivalRate="15.3" meanWaitTime="18.422282852489605" reqDropFraction="0.3188" waitTimeStddev="3.563471263241499"/>
    <simulation meanReqArrivalRate="15.4" meanWaitTime="18.478544164734465" reqDropFraction="0.3231" waitTimeStddev="3.2196778843337257"/>
    <simulation meanReqArrivalRate="15.5" meanWaitTime="18.277224310754065" reqDropFraction="0.3243" waitTimeStddev="3.167657355868182"/>
    <simulation meanReqArrivalRate="15.600000000000001" meanWaitTime="18.593161592502923" reqDropFraction="0.3229" waitTimeStddev="3.2544241292522873"/>
    <simulation meanReqArrivalRate="15.700000000000001" meanWaitTime="17.84338189720798" reqDropFraction="0.3136" waitTimeStddev="3.5288975265172784"/>
    <simulation meanReqArrivalRate="15.8" meanWaitTime="18.549691286200584" reqDropFraction="0.3354" waitTimeStddev="3.4920651611509492"/>
    <simulation meanReqArrivalRate="15.9" meanWaitTime="18.582535708232786" reqDropFraction="0.3375" waitTimeStddev="2.9126076009396407"/>
    <simulation meanReqArrivalRate="16.0" meanWaitTime="18.627709222807862" reqDropFraction="0.3521" waitTimeStddev="3.8185683964973105"/>
    <simulation meanReqArrivalRate="16.1" meanWaitTime="18.522374473031842" reqDropFraction="0.351" waitTimeStddev="3.9581175074235406"/>
    <simulation meanReqArrivalRate="16.200000000000003" meanWaitTime="18.65105204889589" reqDropFraction="0.3506" waitTimeStddev="3.3766345726732303"/>
    <simulation meanReqArrivalRate="16.3" meanWaitTime="18.891422096889652" reqDropFraction="0.3676" waitTimeStddev="3.4990204982490916"/>
    <simulation meanReqArrivalRate="16.4" meanWaitTime="19.10543879722537" reqDropFraction="0.3757" waitTimeStddev="3.0943250204683093"/>
    <simulation meanReqArrivalRate="16.5" meanWaitTime="18.21981750985186" reqDropFraction="0.35" waitTimeStddev="3.1111463298192503"/>
    <simulation meanReqArrivalRate="16.6" meanWaitTime="18.632074195571075" reqDropFraction="0.3677" waitTimeStddev="3.884374113581402"/>
    <simulation meanReqArrivalRate="16.700000000000003" meanWaitTime="18.18626326224397" reqDropFraction="0.3557" waitTimeStddev="3.4299392532850725"/>
    <simulation meanReqArrivalRate="16.8" meanWaitTime="18.74756806243896" reqDropFraction="0.3737" waitTimeStddev="3.5020823988524175"/>
    <simulation meanReqArrivalRate="16.9" meanWaitTime="18.897604801936325" reqDropFraction="0.3825" waitTimeStddev="3.47898833985"/>
    <simulation meanReqArrivalRate="17.0" meanWaitTime="18.81900557489462" reqDropFraction="0.3729" waitTimeStddev="3.1285504230978787"/>
    <simulation meanReqArrivalRate="17.1" meanWaitTime="18.86708390389032" reqDropFraction="0.3796" waitTimeStddev="3.122375062407341"/>
    <simulation meanReqArrivalRate="17.2" meanWaitTime="18.448734277024965" reqDropFraction="0.379" waitTimeStddev="3.5548834834812486"/>
    <simulation meanReqArrivalRate="17.3" meanWaitTime="19.152286325648223" reqDropFraction="0.4025" waitTimeStddev="3.3986250400854736"/>
    <simulation meanReqArrivalRate="17.400000000000002" meanWaitTime="18.92270469151758" reqDropFraction="0.3917" waitTimeStddev="3.498330325548052"/>
    <simulation meanReqArrivalRate="17.5" meanWaitTime="18.619557854742364" reqDropFraction="0.3912" waitTimeStddev="3.1201830583949444"/>
    <simulation meanReqArrivalRate="17.6" meanWaitTime="18.507832247732455" reqDropFraction="0.402" waitTimeStddev="3.574469404993746"/>
    <simulation meanReqArrivalRate="17.7" meanWaitTime="18.53651166500634" reqDropFraction="0.3995" waitTimeStddev="3.2079313582331754"/>
    <simulation meanReqArrivalRate="17.8" meanWaitTime="18.762113573507182" reqDropFraction="0.3917" waitTimeStddev="3.334354723031177"/>
    <simulation meanReqArrivalRate="17.900000000000002" meanWaitTime="18.49076933579066" reqDropFraction="0.3967" waitTimeStddev="2.8584780562227663"/>
    <simulation meanReqArrivalRate="18.0" meanWaitTime="18.329123311084263" reqDropFraction="0.401" waitTimeStddev="3.4115516299120627"/>
    <simulation meanReqArrivalRate="18.1" meanWaitTime="18.52501191127603" reqDropFraction="0.4091" waitTimeStddev="3.376166247831337"/>
    <simulation meanReqArrivalRate="18.2" meanWaitTime="18.640241591296807" reqDropFraction="0.4262" waitTimeStddev="3.4285210150620906"/>
    <simulation meanReqArrivalRate="18.3" meanWaitTime="18.673590716339763" reqDropFraction="0.4263" waitTimeStddev="3.2735588291225075"/>
    <simulation meanReqArrivalRate="18.400000000000002" meanWaitTime="18.434978654113475" reqDropFraction="0.4107" waitTimeStddev="3.4873235191989997"/>
    <simulation meanReqArrivalRate="18.5" meanWaitTime="18.83270893543321" reqDropFraction="0.4282" waitTimeStddev="3.5027976706775283"/>
    <simulation meanReqArrivalRate="18.6" meanWaitTime="18.97756013519837" reqDropFraction="0.4471" waitTimeStddev="3.2851770384785266"/>
    <simulation meanReqArrivalRate="18.7" meanWaitTime="18.55718277597812" reqDropFraction="0.4262" waitTimeStddev="3.1121624130006977"/>
    <simulation meanReqArrivalRate="18.8" meanWaitTime="18.550895093527814" reqDropFraction="0.4358" waitTimeStddev="3.3283957525052554"/>
    <simulation meanReqArrivalRate="18.900000000000002" meanWaitTime="19.153160344691592" reqDropFraction="0.4493" waitTimeStddev="3.4073845865529875"/>
    <simulation meanReqArrivalRate="19.0" meanWaitTime="19.23342761059209" reqDropFraction="0.461" waitTimeStddev="2.980803403445717"/>
    <simulation meanReqArrivalRate="19.1" meanWaitTime="18.505705694078934" reqDropFraction="0.4482" waitTimeStddev="3.256900424906173"/>
    <simulation meanReqArrivalRate="19.2" meanWaitTime="18.231799171784317" reqDropFraction="0.4339" waitTimeStddev="3.516023465821284"/>
    <simulation meanReqArrivalRate="19.3" meanWaitTime="18.531837266185132" reqDropFraction="0.4587" waitTimeStddev="3.203323128859145"/>
    <simulation meanReqArrivalRate="19.400000000000002" meanWaitTime="18.80801053129509" reqDropFraction="0.4604" waitTimeStddev="3.6836806472749952"/>
    <simulation meanReqArrivalRate="19.5" meanWaitTime="18.338777300670454" reqDropFraction="0.4438" waitTimeStddev="3.619172042425727"/>
    <simulation meanReqArrivalRate="19.6" meanWaitTime="18.945103477624418" reqDropFraction="0.4578" waitTimeStddev="3.0377635187347822"/>
    <simulation meanReqArrivalRate="19.7" meanWaitTime="19.06523262674528" reqDropFraction="0.4816" waitTimeStddev="3.557394845188852"/>
    <simulation meanReqArrivalRate="19.8" meanWaitTime="18.679237429811632" reqDropFraction="0.4729" waitTimeStddev="2.9811170708985935"/>
    <simulation meanReqArrivalRate="19.900000000000002" meanWaitTime="18.57788470794005" reqDropFraction="0.4629" waitTimeStddev="3.0820684249175683"/>
    <simulation meanReqArrivalRate="20.0" meanWaitTime="18.59808966720125" reqDropFraction="0.4667" waitTimeStddev="3.326776519851394"/>
    <simulation meanReqArrivalRate="20.1" meanWaitTime="18.687156996699084" reqDropFraction="0.4675" waitTimeStddev="3.260916569261859"/>
    <simulation meanReqArrivalRate="20.200000000000003" meanWaitTime="18.610552410070678" reqDropFraction="0.471" waitTimeStddev="3.306665575339172"/>
    <simulation meanReqArrivalRate="20.3" meanWaitTime="18.72618708032523" reqDropFraction="0.4799" waitTimeStddev="3.572176894102313"/>
    <simulation meanReqArrivalRate="20.400000000000002" meanWaitTime="18.866767270313872" reqDropFraction="0.4797" waitTimeStddev="3.105783029238736"/>
    <simulation meanReqArrivalRate="20.5" meanWaitTime="18.77056650113907" reqDropFraction="0.4802" waitTimeStddev="3.069682931041708"/>
    <simulation meanReqArrivalRate="20.6" meanWaitTime="18.906601775274492" reqDropFraction="0.4879" waitTimeStddev="3.155331251392847"/>
    <simulation meanReqArrivalRate="20.700000000000003" meanWaitTime="18.64212419802753" reqDropFraction="0.4713" waitTimeStddev="3.134052353623214"/>
    <simulation meanReqArrivalRate="20.8" meanWaitTime="18.696957521668065" reqDropFraction="0.4861" waitTimeStddev="3.177190391505072"/>
    <simulation meanReqArrivalRate="20.900000000000002" meanWaitTime="18.571839982749744" reqDropFraction="0.4849" waitTimeStddev="3.467961215261749"/>
    <simulation meanReqArrivalRate="21.0" meanWaitTime="19.117035998191017" reqDropFraction="0.4952" waitTimeStddev="3.171217301501576"/>
    <simulation meanReqArrivalRate="21.1" meanWaitTime="19.03319403101794" reqDropFraction="0.5036" waitTimeStddev="3.552067575582301"/>
    <simulation meanReqArrivalRate="21.200000000000003" meanWaitTime="18.732392027010537" reqDropFraction="0.4876" waitTimeStddev="3.1983510342953365"/>
    <simulation meanReqArrivalRate="21.3" meanWaitTime="18.378807981085828" reqDropFraction="0.4901" waitTimeStddev="3.5560879024546597"/>
    <simulation meanReqArrivalRate="21.400000000000002" meanWaitTime="18.29747640625341" reqDropFraction="0.4866" waitTimeStddev="2.7503866575545546"/>
    <simulation meanReqArrivalRate="21.5" meanWaitTime="18.469182947759563" reqDropFraction="0.4948" waitTimeStddev="3.077675965845632"/>
    <simulation meanReqArrivalRate="21.6" meanWaitTime="18.287168284362554" reqDropFraction="0.4861" waitTimeStddev="3.1721687536112224"/>
    <simulation meanReqArrivalRate="21.700000000000003" meanWaitTime="19.007229346835953" reqDropFraction="0.508" waitTimeStddev="3.5113905374201275"/>
    <simulation meanReqArrivalRate="21.8" meanWaitTime="18.427364237484202" reqDropFraction="0.5075" waitTimeStddev="3.0277830729459816"/>
    <simulation meanReqArrivalRate="21.900000000000002" meanWaitTime="18.96194772050558" reqDropFraction="0.5158" waitTimeStddev="3.2178478137297186"/>
    <simulation meanReqArrivalRate="22.0" meanWaitTime="18.751225734695726" reqDropFraction="0.5282" waitTimeStddev="3.5670261944762442"/>
    <simulation meanReqArrivalRate="22.1" meanWaitTime="18.58919488262184" reqDropFraction="0.5226" waitTimeStddev="3.1630375306704344"/>
    <simulation meanReqArrivalRate="22.200000000000003" meanWaitTime="18.13612801251886" reqDropFraction="0.5054" waitTimeStddev="3.1978629213715526"/>
    <simulation meanReqArrivalRate="22.3" meanWaitTime="18.776324208823652" reqDropFraction="0.5198" waitTimeStddev="3.3198365459546153"/>
    <simulation meanReqArrivalRate="22.400000000000002" meanWaitTime="18.280706268050853" reqDropFraction="0.5194" waitTimeStddev="3.1472548182764783"/>
    <simulation meanReqArrivalRate="22.5" meanWaitTime="19.059942438875684" reqDropFraction="0.5368" waitTimeStddev="3.0594090585082014"/>
    <simulation meanReqArrivalRate="22.6" meanWaitTime="19.039215724358773" reqDropFraction="0.5319" waitTimeStddev="3.6388351542028206"/>
    <simulation meanReqArrivalRate="22.700000000000003" meanWaitTime="18.373323055727482" reqDropFraction="0.5154" waitTimeStddev="3.1369241973571906"/>
    <simulation meanReqArrivalRate="22.8" meanWaitTime="18.975099384210363" reqDropFraction="0.5283" waitTimeStddev="3.0830315420327143"/>
    <simulation meanReqArrivalRate="22.900000000000002" meanWaitTime="18.47383017501535" reqDropFraction="0.5254" waitTimeStddev="2.888522940208489"/>
    <simulation meanReqArrivalRate="23.0" meanWaitTime="18.789520827602296" reqDropFraction="0.5394" waitTimeStddev="3.541069410536268"/>
    <simulation meanReqArrivalRate="23.1" meanWaitTime="18.49053299699211" reqDropFraction="0.5267" waitTimeStddev="3.078614677306847"/>
    <simulation meanReqArrivalRate="23.200000000000003" meanWaitTime="18.96407417478014" reqDropFraction="0.5465" waitTimeStddev="3.4707383964332617"/>
    <simulation meanReqArrivalRate="23.3" meanWaitTime="18.502624839516393" reqDropFraction="0.5339" waitTimeStddev="3.4794794523523445"/>
    <simulation meanReqArrivalRate="23.400000000000002" meanWaitTime="18.660268941087047" reqDropFraction="0.5462" waitTimeStddev="3.5805789416762943"/>
    <simulation meanReqArrivalRate="23.5" meanWaitTime="19.167965561792855" reqDropFraction="0.5556" waitTimeStddev="3.5283981330661542"/>
    <simulation meanReqArrivalRate="23.6" meanWaitTime="19.409021669190757" reqDropFraction="0.5601" waitTimeStddev="3.4602621672549927"/>
    <simulation meanReqArrivalRate="23.700000000000003" meanWaitTime="18.71639486051547" reqDropFraction="0.5482" waitTimeStddev="3.1578073726669533"/>
    <simulation meanReqArrivalRate="23.8" meanWaitTime="18.585637786352322" reqDropFraction="0.5404" waitTimeStddev="3.182702190413097"/>
    <simulation meanReqArrivalRate="23.900000000000002" meanWaitTime="18.422465030174873" reqDropFraction="0.5455" waitTimeStddev="3.3313234810474555"/>
    <simulation meanReqArrivalRate="24.0" meanWaitTime="18.507820910403776" reqDropFraction="0.5486" waitTimeStddev="3.243221158811192"/>
    <simulation meanReqArrivalRate="24.1" meanWaitTime="18.815318614139347" reqDropFraction="0.5613" waitTimeStddev="3.386424009275445"/>
    <simulation meanReqArrivalRate="24.200000000000003" meanWaitTime="18.501038340598306" reqDropFraction="0.5582" waitTimeStddev="3.0316551576464166"/>
    <simulation meanReqArrivalRate="24.3" meanWaitTime="19.051190754201556" reqDropFraction="0.5667" waitTimeStddev="3.327949536023817"/>
    <simulation meanReqArrivalRate="24.400000000000002" meanWaitTime="18.92980714217812" reqDropFraction="0.5714" waitTimeStddev="3.6333295982544365"/>
    <simulation meanReqArrivalRate="24.5" meanWaitTime="18.953556726737357" reqDropFraction="0.5696" waitTimeStddev="3.4650988535133305"/>
    <simulation meanReqArrivalRate="24.6" meanWaitTime="18.12017934693618" reqDropFraction="0.5552" waitTimeStddev="3.2504743005172663"/>
    <simulation meanReqArrivalRate="24.700000000000003" meanWaitTime="19.176086896630498" reqDropFraction="0.5772" waitTimeStddev="3.4148031600989124"/>
    <simulation meanReqArrivalRate="24.8" meanWaitTime="18.69975628579673" reqDropFraction="0.5675" waitTimeStddev="3.477716471114796"/>
    <simulation meanReqArrivalRate="24.900000000000002" meanWaitTime="18.662014774195406" reqDropFraction="0.5726" waitTimeStddev="3.197097587280581"/>
    <simulation meanReqArrivalRate="25.0" meanWaitTime="18.730131345088854" reqDropFraction="0.5765" waitTimeStddev="3.512974254131563"/>
    <simulation meanReqArrivalRate="25.1" meanWaitTime="19.09555445439909" reqDropFraction="0.5834" waitTimeStddev="3.609619971203718"/>
    <simulation meanReqArrivalRate="25.200000000000003" meanWaitTime="18.682565547009325" reqDropFraction="0.5732" waitTimeStddev="3.7564873069303437"/>
    <simulation meanReqArrivalRate="25.3" meanWaitTime="18.965081353749078" reqDropFraction="0.5821" waitTimeStddev="3.242690520508788"/>
    <simulation meanReqArrivalRate="25.400000000000002" meanWaitTime="18.90938117933679" reqDropFraction="0.584" waitTimeStddev="3.173182785822898"/>
    <simulation meanReqArrivalRate="25.5" meanWaitTime="19.264646995535653" reqDropFraction="0.5876" waitTimeStddev="3.4520306521030313"/>
    <simulation meanReqArrivalRate="25.6" meanWaitTime="18.70815285129417" reqDropFraction="0.5708" waitTimeStddev="3.1888346911476764"/>
    <simulation meanReqArrivalRate="25.700000000000003" meanWaitTime="18.910011015800343" reqDropFraction="0.5867" waitTimeStddev="3.644598120801506"/>
    <simulation meanReqArrivalRate="25.8" meanWaitTime="18.605592301952104" reqDropFraction="0.5754" waitTimeStddev="3.028444393058213"/>
    <simulation meanReqArrivalRate="25.900000000000002" meanWaitTime="19.115206962538945" reqDropFraction="0.5939" waitTimeStddev="3.4050687677367244"/>
    <simulation meanReqArrivalRate="26.0" meanWaitTime="18.84448066973139" reqDropFraction="0.5901" waitTimeStddev="3.4396622273802344"/>
    <simulation meanReqArrivalRate="26.1" meanWaitTime="18.551361383645382" reqDropFraction="0.5796" waitTimeStddev="3.2776584536178883"/>
    <simulation meanReqArrivalRate="26.200000000000003" meanWaitTime="18.612316696297412" reqDropFraction="0.5924" waitTimeStddev="3.3158745011206996"/>
    <simulation meanReqArrivalRate="26.3" meanWaitTime="18.521952148929465" reqDropFraction="0.5931" waitTimeStddev="3.2187447973945655"/>
    <simulation meanReqArrivalRate="26.400000000000002" meanWaitTime="19.11607787897755" reqDropFraction="0.5956" waitTimeStddev="3.4493112233223306"/>
    <simulation meanReqArrivalRate="26.5" meanWaitTime="18.35864952306623" reqDropFraction="0.5959" waitTimeStddev="3.557021970947163"/>
    <simulation meanReqArrivalRate="26.6" meanWaitTime="18.94496497335087" reqDropFraction="0.6054" waitTimeStddev="3.5917802132203858"/>
    <simulation meanReqArrivalRate="26.700000000000003" meanWaitTime="18.73254895245802" reqDropFraction="0.5957" waitTimeStddev="3.2607178945422035"/>
    <simulation meanReqArrivalRate="26.8" meanWaitTime="19.114383538609655" reqDropFraction="0.6021" waitTimeStddev="3.334751380460049"/>
    <simulation meanReqArrivalRate="26.900000000000002" meanWaitTime="18.130015909281195" reqDropFraction="0.5943" waitTimeStddev="3.122178015795583"/>
    <simulation meanReqArrivalRate="27.0" meanWaitTime="18.92844646509043" reqDropFraction="0.6085" waitTimeStddev="3.210319689325462"/>
    <simulation meanReqArrivalRate="27.1" meanWaitTime="18.807504949999323" reqDropFraction="0.5995" waitTimeStddev="3.054542070576489"/>
    <simulation meanReqArrivalRate="27.200000000000003" meanWaitTime="18.850962115396893" reqDropFraction="0.6068" waitTimeStddev="3.2425710360575977"/>
    <simulation meanReqArrivalRate="27.3" meanWaitTime="18.64306417830319" reqDropFraction="0.6076" waitTimeStddev="3.5927403360920205"/>
    <simulation meanReqArrivalRate="27.400000000000002" meanWaitTime="18.65360203670067" reqDropFraction="0.6068" waitTimeStddev="3.229477116941353"/>
    <simulation meanReqArrivalRate="27.5" meanWaitTime="19.154559396979938" reqDropFraction="0.6159" waitTimeStddev="3.4589758705112956"/>
    <simulation meanReqArrivalRate="27.6" meanWaitTime="18.19899360026233" reqDropFraction="0.5982" waitTimeStddev="3.083032533566701"/>
    <simulation meanReqArrivalRate="27.700000000000003" meanWaitTime="19.300708201063607" reqDropFraction="0.6189" waitTimeStddev="3.267810058349801"/>
    <simulation meanReqArrivalRate="27.8" meanWaitTime="18.686741390376483" reqDropFraction="0.6119" waitTimeStddev="3.0757822666127272"/>
    <simulation meanReqArrivalRate="27.900000000000002" meanWaitTime="19.220200670004036" reqDropFraction="0.6216" waitTimeStddev="3.2727495003527505"/>
    <simulation meanReqArrivalRate="28.0" meanWaitTime="18.716604978364135" reqDropFraction="0.6124" waitTimeStddev="3.0661586868179125"/>
    <simulation meanReqArrivalRate="28.1" meanWaitTime="18.795878967912234" reqDropFraction="0.617" waitTimeStddev="3.2611748825110127"/>
    <simulation meanReqArrivalRate="28.200000000000003" meanWaitTime="18.76884686372107" reqDropFraction="0.6152" waitTimeStddev="3.128098468389516"/>
    <simulation meanReqArrivalRate="28.3" meanWaitTime="18.813057499980623" reqDropFraction="0.6199" waitTimeStddev="3.466895443369603"/>
    <simulation meanReqArrivalRate="28.400000000000002" meanWaitTime="18.863167545248153" reqDropFraction="0.6263" waitTimeStddev="3.546819726440102"/>
    <simulation meanReqArrivalRate="28.5" meanWaitTime="18.82910360753282" reqDropFraction="0.6216" waitTimeStddev="3.495488878198185"/>
    <simulation meanReqArrivalRate="28.6" meanWaitTime="18.790555065592297" reqDropFraction="0.6245" waitTimeStddev="3.2543554218270367"/>
    <simulation meanReqArrivalRate="28.700000000000003" meanWaitTime="18.11005132615895" reqDropFraction="0.6114" waitTimeStddev="3.3705680611471687"/>
    <simulation meanReqArrivalRate="28.8" meanWaitTime="18.73813032145505" reqDropFraction="0.6272" waitTimeStddev="3.0861287607974117"/>
    <simulation meanReqArrivalRate="28.900000000000002" meanWaitTime="18.805403565148602" reqDropFraction="0.6269" waitTimeStddev="3.6399910463038854"/>
    <simulation meanReqArrivalRate="29.0" meanWaitTime="18.422923844221643" reqDropFraction="0.6242" waitTimeStddev="3.2865690506391725"/>
    <simulation meanReqArrivalRate="29.1" meanWaitTime="18.77746105665676" reqDropFraction="0.6296" waitTimeStddev="3.262945098514112"/>
    <simulation meanReqArrivalRate="29.200000000000003" meanWaitTime="18.7065598485441" reqDropFraction="0.6289" waitTimeStddev="3.0817276108963716"/>
    <simulation meanReqArrivalRate="29.3" meanWaitTime="19.074730026289995" reqDropFraction="0.6401" waitTimeStddev="3.4521170034942656"/>
    <simulation meanReqArrivalRate="29.400000000000002" meanWaitTime="18.962936763719412" reqDropFraction="0.6434" waitTimeStddev="3.5194840283244355"/>
    <simulation meanReqArrivalRate="29.5" meanWaitTime="18.878783008370196" reqDropFraction="0.6451" waitTimeStddev="3.7297206176458495"/>
    <simulation meanReqArrivalRate="29.6" meanWaitTime="18.707883578200324" reqDropFraction="0.6324" waitTimeStddev="3.2695755627831495"/>
    <simulation meanReqArrivalRate="29.700000000000003" meanWaitTime="18.989557030455646" reqDropFraction="0.6415" waitTimeStddev="3.188115815561916"/>
    <simulation meanReqArrivalRate="29.8" meanWaitTime="18.667592775535297" reqDropFraction="0.6403" waitTimeStddev="3.225907804030039"/>
    <simulation meanReqArrivalRate="29.900000000000002" meanWaitTime="19.084418638176754" reqDropFraction="0.6426" waitTimeStddev="3.509469997317115"/>
    <simulation meanReqArrivalRate="30.0" meanWaitTime="18.426681092355583" reqDropFraction="0.6374" waitTimeStddev="3.461157707447468"/>
    <simulation meanReqArrivalRate="30.1" meanWaitTime="18.601658580178555" reqDropFraction="0.6345" waitTimeStddev="3.5914432846977813"/>
    <simulation meanReqArrivalRate="30.200000000000003" meanWaitTime="18.896938150154263" reqDropFraction="0.6528" waitTimeStddev="3.261490237506037"/>
    <simulation meanReqArrivalRate="30.3" meanWaitTime="18.260600293283883" reqDropFraction="0.6344" waitTimeStddev="3.094381205551987"/>
    <simulation meanReqArrivalRate="30.400000000000002" meanWaitTime="18.89470904363363" reqDropFraction="0.645" waitTimeStddev="3.4796159731878262"/>
    <simulation meanReqArrivalRate="30.5" meanWaitTime="18.979004741148827" reqDropFraction="0.6543" waitTimeStddev="3.82297825130542"/>
    <simulation meanReqArrivalRate="30.6" meanWaitTime="19.10981380274536" reqDropFraction="0.654" waitTimeStddev="3.4451507838582978"/>
    <simulation meanReqArrivalRate="30.700000000000003" meanWaitTime="18.780157796634004" reqDropFraction="0.644" waitTimeStddev="3.2336386187869928"/>
    <simulation meanReqArrivalRate="30.8" meanWaitTime="18.273239144695516" reqDropFraction="0.6404" waitTimeStddev="3.4155058376879013"/>
    <simulation meanReqArrivalRate="30.900000000000002" meanWaitTime="18.76068912218371" reqDropFraction="0.6565" waitTimeStddev="3.7923047710663753"/>
    <simulation meanReqArrivalRate="31.0" meanWaitTime="19.43926872273892" reqDropFraction="0.6591" waitTimeStddev="3.4860148059686358"/>
    <simulation meanReqArrivalRate="31.1" meanWaitTime="18.354468453877285" reqDropFraction="0.6473" waitTimeStddev="3.537972164346191"/>
    <simulation meanReqArrivalRate="31.200000000000003" meanWaitTime="18.920373459844427" reqDropFraction="0.6487" waitTimeStddev="3.4165970547712807"/>
    <simulation meanReqArrivalRate="31.3" meanWaitTime="18.81423947252676" reqDropFraction="0.6515" waitTimeStddev="3.452523967379639"/>
    <simulation meanReqArrivalRate="31.400000000000002" meanWaitTime="18.373202147061107" reqDropFraction="0.6479" waitTimeStddev="3.3889931187243003"/>
    <simulation meanReqArrivalRate="31.5" meanWaitTime="18.555533012012788" reqDropFraction="0.6541" waitTimeStddev="3.386857002621066"/>
    <simulation meanReqArrivalRate="31.6" meanWaitTime="18.772556006666274" reqDropFraction="0.6577" waitTimeStddev="3.4566501663682336"/>
    <simulation meanReqArrivalRate="31.700000000000003" meanWaitTime="18.409238443914713" reqDropFraction="0.653" waitTimeStddev="3.8037039032075564"/>
    <simulation meanReqArrivalRate="31.8" meanWaitTime="19.064414335684976" reqDropFraction="0.6649" waitTimeStddev="3.118700217381803"/>
    <simulation meanReqArrivalRate="31.900000000000002" meanWaitTime="18.649859029699503" reqDropFraction="0.6605" waitTimeStddev="3.56362118518847"/>
    <simulation meanReqArrivalRate="32.0" meanWaitTime="18.68692658701028" reqDropFraction="0.6584" waitTimeStddev="3.3147641623655613"/>
    <simulation meanReqArrivalRate="32.1" meanWaitTime="18.476878013037524" reqDropFraction="0.6599" waitTimeStddev="3.378798517696365"/>
    <simulation meanReqArrivalRate="32.2" meanWaitTime="19.414624594786147" reqDropFraction="0.6768" waitTimeStddev="3.5792564685121206"/>
    <simulation meanReqArrivalRate="32.3" meanWaitTime="19.032572931135476" reqDropFraction="0.6711" waitTimeStddev="3.9349685080890726"/>
    <simulation meanReqArrivalRate="32.400000000000006" meanWaitTime="18.460592748475772" reqDropFraction="0.6583" waitTimeStddev="3.209576652957306"/>
    <simulation meanReqArrivalRate="32.5" meanWaitTime="19.26043360089495" reqDropFraction="0.6709" waitTimeStddev="3.5698930164122222"/>
    <simulation meanReqArrivalRate="32.6" meanWaitTime="18.24101880817387" reqDropFraction="0.6565" waitTimeStddev="3.3785992918411334"/>
    <simulation meanReqArrivalRate="32.7" meanWaitTime="18.755985228180176" reqDropFraction="0.6656" waitTimeStddev="3.5703568753161057"/>
    <simulation meanReqArrivalRate="32.8" meanWaitTime="19.18808244572035" reqDropFraction="0.6743" waitTimeStddev="3.534460777544086"/>
    <simulation meanReqArrivalRate="32.900000000000006" meanWaitTime="18.370705934898087" reqDropFraction="0.6623" waitTimeStddev="3.367297377904876"/>
    <simulation meanReqArrivalRate="33.0" meanWaitTime="19.241432193718833" reqDropFraction="0.6806" waitTimeStddev="3.675954757930685"/>
    <simulation meanReqArrivalRate="33.1" meanWaitTime="18.77768890666853" reqDropFraction="0.6715" waitTimeStddev="3.79266591970116"/>
    <simulation meanReqArrivalRate="33.2" meanWaitTime="18.691307294849985" reqDropFraction="0.6682" waitTimeStddev="3.2454347878740926"/>
    <simulation meanReqArrivalRate="33.300000000000004" meanWaitTime="18.8577503761882" reqDropFraction="0.6779" waitTimeStddev="3.5427955311685855"/>
    <simulation meanReqArrivalRate="33.4" meanWaitTime="19.317138115886" reqDropFraction="0.6778" waitTimeStddev="3.9482813695159917"/>
    <simulation meanReqArrivalRate="33.5" meanWaitTime="18.63078851639092" reqDropFraction="0.6788" waitTimeStddev="3.2939477812323084"/>
    <simulation meanReqArrivalRate="33.6" meanWaitTime="18.512286220508507" reqDropFraction="0.6735" waitTimeStddev="3.696150415998044"/>
    <simulation meanReqArrivalRate="33.7" meanWaitTime="18.663675302050862" reqDropFraction="0.6757" waitTimeStddev="3.382022235416592"/>
    <simulation meanReqArrivalRate="33.800000000000004" meanWaitTime="18.583917980694398" reqDropFraction="0.6712" waitTimeStddev="3.304461286591148"/>
    <simulation meanReqArrivalRate="33.9" meanWaitTime="18.662720129542105" reqDropFraction="0.6809" waitTimeStddev="3.4575996016090755"/>
    <simulation meanReqArrivalRate="34.0" meanWaitTime="19.334841593656645" reqDropFraction="0.6882" waitTimeStddev="3.9030191892050383"/>
    <simulation meanReqArrivalRate="34.1" meanWaitTime="18.90841788673225" reqDropFraction="0.6854" waitTimeStddev="3.6413277875140704"/>
    <simulation meanReqArrivalRate="34.2" meanWaitTime="19.09908610423438" reqDropFraction="0.6863" waitTimeStddev="3.587331262409007"/>
    <simulation meanReqArrivalRate="34.300000000000004" meanWaitTime="18.924856756895377" reqDropFraction="0.691" waitTimeStddev="3.6932377975449433"/>
    <simulation meanReqArrivalRate="34.4" meanWaitTime="18.976583174683288" reqDropFraction="0.6849" waitTimeStddev="3.4401052334165994"/>
    <simulation meanReqArrivalRate="34.5" meanWaitTime="19.077127928183668" reqDropFraction="0.6931" waitTimeStddev="3.46344480362764"/>
    <simulation meanReqArrivalRate="34.6" meanWaitTime="18.472068517671058" reqDropFraction="0.6866" waitTimeStddev="3.394076068431872"/>
    <simulation meanReqArrivalRate="34.7" meanWaitTime="18.564450193876272" reqDropFraction="0.68" waitTimeStddev="3.627652367039898"/>
    <simulation meanReqArrivalRate="34.800000000000004" meanWaitTime="18.754148660774035" reqDropFraction="0.6818" waitTimeStddev="3.5724560677353216"/>
    <simulation meanReqArrivalRate="34.9" meanWaitTime="18.566398483893604" reqDropFraction="0.6887" waitTimeStddev="3.720615100364904"/>
    <simulation meanReqArrivalRate="35.0" meanWaitTime="19.235527625926235" reqDropFraction="0.6989" waitTimeStddev="3.708291281191872"/>
    <simulation meanReqArrivalRate="35.1" meanWaitTime="18.248331947579626" reqDropFraction="0.6812" waitTimeStddev="3.4240455192066928"/>
    <simulation meanReqArrivalRate="35.2" meanWaitTime="18.3034782710471" reqDropFraction="0.6796" waitTimeStddev="3.562575926151355"/>
    <simulation meanReqArrivalRate="35.300000000000004" meanWaitTime="18.6670711736458" reqDropFraction="0.6911" waitTimeStddev="3.268571682623925"/>
    <simulation meanReqArrivalRate="35.4" meanWaitTime="18.51239187367075" reqDropFraction="0.6908" waitTimeStddev="3.328073476388792"/>
    <simulation meanReqArrivalRate="35.5" meanWaitTime="18.875357537429153" reqDropFraction="0.6957" waitTimeStddev="3.464235702510419"/>
    <simulation meanReqArrivalRate="35.6" meanWaitTime="18.885821281294383" reqDropFraction="0.6966" waitTimeStddev="3.5002109111486104"/>
    <simulation meanReqArrivalRate="35.7" meanWaitTime="18.319101995045532" reqDropFraction="0.6882" waitTimeStddev="3.3785062086784383"/>
    <simulation meanReqArrivalRate="35.800000000000004" meanWaitTime="18.397647099476092" reqDropFraction="0.6929" waitTimeStddev="3.387496755268216"/>
    <simulation meanReqArrivalRate="35.9" meanWaitTime="19.204316694143397" reqDropFraction="0.7055" waitTimeStddev="3.9433304831640186"/>
    <simulation meanReqArrivalRate="36.0" meanWaitTime="18.910629363772262" reqDropFraction="0.7017" waitTimeStddev="3.791691456760366"/>
    <simulation meanReqArrivalRate="36.1" meanWaitTime="18.636007791871485" reqDropFraction="0.6952" waitTimeStddev="3.7079498878741606"/>
    <simulation meanReqArrivalRate="36.2" meanWaitTime="18.665557107917966" reqDropFraction="0.7012" waitTimeStddev="3.3142909289070555"/>
    <simulation meanReqArrivalRate="36.300000000000004" meanWaitTime="17.908102856448487" reqDropFraction="0.69" waitTimeStddev="3.6749819979681146"/>
    <simulation meanReqArrivalRate="36.4" meanWaitTime="18.247744046315635" reqDropFraction="0.6925" waitTimeStddev="3.3516462998109313"/>
    <simulation meanReqArrivalRate="36.5" meanWaitTime="18.31833755825659" reqDropFraction="0.6965" waitTimeStddev="3.213453558824227"/>
    <simulation meanReqArrivalRate="36.6" meanWaitTime="18.934830933549563" reqDropFraction="0.709" waitTimeStddev="3.56821563467075"/>
    <simulation meanReqArrivalRate="36.7" meanWaitTime="18.79373872216873" reqDropFraction="0.7005" waitTimeStddev="3.4837590336481004"/>
    <simulation meanReqArrivalRate="36.800000000000004" meanWaitTime="18.953356844524865" reqDropFraction="0.703" waitTimeStddev="3.471412131303626"/>
    <simulation meanReqArrivalRate="36.9" meanWaitTime="18.856399060437482" reqDropFraction="0.7071" waitTimeStddev="3.533744819247345"/>
    <simulation meanReqArrivalRate="37.0" meanWaitTime="18.712735292641696" reqDropFraction="0.7011" waitTimeStddev="3.667971402784524"/>
    <simulation meanReqArrivalRate="37.1" meanWaitTime="18.097585838879965" reqDropFraction="0.6969" waitTimeStddev="3.118138099419765"/>
    <simulation meanReqArrivalRate="37.2" meanWaitTime="19.05602403404418" reqDropFraction="0.7048" waitTimeStddev="3.1183649389159767"/>
    <simulation meanReqArrivalRate="37.300000000000004" meanWaitTime="19.14324104029344" reqDropFraction="0.7121" waitTimeStddev="3.3842712248794906"/>
    <simulation meanReqArrivalRate="37.4" meanWaitTime="18.600912619065934" reqDropFraction="0.7026" waitTimeStddev="3.6937678054225174"/>
    <simulation meanReqArrivalRate="37.5" meanWaitTime="18.454653944568175" reqDropFraction="0.7083" waitTimeStddev="3.5696668019984332"/>
    <simulation meanReqArrivalRate="37.6" meanWaitTime="18.899345960751706" reqDropFraction="0.7152" waitTimeStddev="3.7423185123613143"/>
    <simulation meanReqArrivalRate="37.7" meanWaitTime="18.49171948258123" reqDropFraction="0.7066" waitTimeStddev="3.4651823315968997"/>
    <simulation meanReqArrivalRate="37.800000000000004" meanWaitTime="18.69518549725254" reqDropFraction="0.7109" waitTimeStddev="3.4760017145926625"/>
    <simulation meanReqArrivalRate="37.9" meanWaitTime="18.339362761244377" reqDropFraction="0.7044" waitTimeStddev="3.4389199081430406"/>
    <simulation meanReqArrivalRate="38.0" meanWaitTime="18.66051917381785" reqDropFraction="0.7104" waitTimeStddev="3.6370108723936085"/>
    <simulation meanReqArrivalRate="38.1" meanWaitTime="18.300311636907427" reqDropFraction="0.7064" waitTimeStddev="3.3873149013164774"/>
    <simulation meanReqArrivalRate="38.2" meanWaitTime="18.73325858001779" reqDropFraction="0.717" waitTimeStddev="3.8840290333096266"/>
    <simulation meanReqArrivalRate="38.300000000000004" meanWaitTime="19.024615307919692" reqDropFraction="0.7206" waitTimeStddev="3.5905821177014547"/>
    <simulation meanReqArrivalRate="38.4" meanWaitTime="18.722205771441576" reqDropFraction="0.7123" waitTimeStddev="3.588059349142955"/>
    <simulation meanReqArrivalRate="38.5" meanWaitTime="18.44476209059244" reqDropFraction="0.7145" waitTimeStddev="4.147575459653427"/>
    <simulation meanReqArrivalRate="38.6" meanWaitTime="18.673849931010317" reqDropFraction="0.7122" waitTimeStddev="3.3486949429564596"/>
    <simulation meanReqArrivalRate="38.7" meanWaitTime="18.80570929413043" reqDropFraction="0.718" waitTimeStddev="3.6918864813575736"/>
    <simulation meanReqArrivalRate="38.800000000000004" meanWaitTime="18.62200560380442" reqDropFraction="0.7171" waitTimeStddev="3.3847435461785285"/>
    <simulation meanReqArrivalRate="38.9" meanWaitTime="18.496599772358397" reqDropFraction="0.7128" waitTimeStddev="3.7039716232022872"/>
    <simulation meanReqArrivalRate="39.0" meanWaitTime="18.4349302194161" reqDropFraction="0.7176" waitTimeStddev="3.6421239895315005"/>
    <simulation meanReqArrivalRate="39.1" meanWaitTime="18.632853307781946" reqDropFraction="0.7189" waitTimeStddev="3.840444247293989"/>
    <simulation meanReqArrivalRate="39.2" meanWaitTime="18.314056285429963" reqDropFraction="0.7157" waitTimeStddev="3.4371726777208544"/>
    <simulation meanReqArrivalRate="39.300000000000004" meanWaitTime="18.725199552878024" reqDropFraction="0.7214" waitTimeStddev="3.7760417481548925"/>
    <simulation meanReqArrivalRate="39.400000000000006" meanWaitTime="18.77007343055606" reqDropFraction="0.7243" waitTimeStddev="3.9302123172731833"/>
    <simulation meanReqArrivalRate="39.5" meanWaitTime="18.953897815390544" reqDropFraction="0.7178" waitTimeStddev="3.5436610435270466"/>
    <simulation meanReqArrivalRate="39.6" meanWaitTime="18.260067791990174" reqDropFraction="0.7175" waitTimeStddev="3.5016771731707097"/>
    <simulation meanReqArrivalRate="39.7" meanWaitTime="18.504801961629724" reqDropFraction="0.7164" waitTimeStddev="3.4457966776866766"/>
    <simulation meanReqArrivalRate="39.800000000000004" meanWaitTime="18.66675543410859" reqDropFraction="0.7231" waitTimeStddev="3.2961367967860564"/>
    <simulation meanReqArrivalRate="39.900000000000006" meanWaitTime="18.94670403767792" reqDropFraction="0.7238" waitTimeStddev="3.600296890819429"/>
    <simulation meanReqArrivalRate="40.0" meanWaitTime="18.287342457008027" reqDropFraction="0.7193" waitTimeStddev="3.601141965538715"/>
    <simulation meanReqArrivalRate="40.1" meanWaitTime="18.65259494457654" reqDropFraction="0.7242" waitTimeStddev="3.6924371023775238"/>
    <simulation meanReqArrivalRate="40.2" meanWaitTime="18.81917120711003" reqDropFraction="0.7286" waitTimeStddev="3.8698393924948777"/>
    <simulation meanReqArrivalRate="40.300000000000004" meanWaitTime="18.101640475839627" reqDropFraction="0.7207" waitTimeStddev="3.4038538846328867"/>
    <simulation meanReqArrivalRate="40.400000000000006" meanWaitTime="18.588162878190026" reqDropFraction="0.7328" waitTimeStddev="3.6944221887932653"/>
    <simulation meanReqArrivalRate="40.5" meanWaitTime="18.5139016049902" reqDropFraction="0.7248" waitTimeStddev="3.5653382839275847"/>
    <simulation meanReqArrivalRate="40.6" meanWaitTime="18.074060451536962" reqDropFraction="0.7229" waitTimeStddev="3.430494840666306"/>
    <simulation meanReqArrivalRate="40.7" meanWaitTime="19.085103097558676" reqDropFraction="0.7322" waitTimeStddev="3.6756464340679202"/>
    <simulation meanReqArrivalRate="40.800000000000004" meanWaitTime="18.464882977350953" reqDropFraction="0.7257" waitTimeStddev="3.204467062167229"/>
    <simulation meanReqArrivalRate="40.900000000000006" meanWaitTime="18.30323665077156" reqDropFraction="0.7283" waitTimeStddev="3.3909117632378623"/>
    <simulation meanReqArrivalRate="41.0" meanWaitTime="17.820393865361122" reqDropFraction="0.7193" waitTimeStddev="3.566897127916573"/>
    <simulation meanReqArrivalRate="41.1" meanWaitTime="18.823140248826427" reqDropFraction="0.7314" waitTimeStddev="3.7036969675662443"/>
    <simulation meanReqArrivalRate="41.2" meanWaitTime="18.88767990557695" reqDropFraction="0.7388" waitTimeStddev="3.8888109616894777"/>
    <simulation meanReqArrivalRate="41.300000000000004" meanWaitTime="18.95760886834476" reqDropFraction="0.7363" waitTimeStddev="3.857719669811565"/>
    <simulation meanReqArrivalRate="41.400000000000006" meanWaitTime="19.082665119148714" reqDropFraction="0.7359" waitTimeStddev="3.7613280926891304"/>
    <simulation meanReqArrivalRate="41.5" meanWaitTime="18.85777379860006" reqDropFraction="0.7403" waitTimeStddev="3.9209282816956366"/>
    <simulation meanReqArrivalRate="41.6" meanWaitTime="18.526241899889403" reqDropFraction="0.7337" waitTimeStddev="3.4629395911957905"/>
    <simulation meanReqArrivalRate="41.7" meanWaitTime="17.937896237626283" reqDropFraction="0.7223" waitTimeStddev="3.6036987848793767"/>
    <simulation meanReqArrivalRate="41.800000000000004" meanWaitTime="18.323749509538153" reqDropFraction="0.7305" waitTimeStddev="3.396152733400246"/>
    <simulation meanReqArrivalRate="41.900000000000006" meanWaitTime="18.282804223675303" reqDropFraction="0.7304" waitTimeStddev="3.7075054557390885"/>
    <simulation meanReqArrivalRate="42.0" meanWaitTime="19.000310278169948" reqDropFraction="0.7461" waitTimeStddev="3.814860982505179"/>
    <simulation meanReqArrivalRate="42.1" meanWaitTime="18.520711246004407" reqDropFraction="0.7332" waitTimeStddev="3.5577951115061417"/>
    <simulation meanReqArrivalRate="42.2" meanWaitTime="19.30992317920115" reqDropFraction="0.746" waitTimeStddev="3.8072728926324553"/>
    <simulation meanReqArrivalRate="42.300000000000004" meanWaitTime="18.42546404107996" reqDropFraction="0.7359" waitTimeStddev="3.3016775418791413"/>
    <simulation meanReqArrivalRate="42.400000000000006" meanWaitTime="18.51267302702127" reqDropFraction="0.7396" waitTimeStddev="3.6384108119141567"/>
    <simulation meanReqArrivalRate="42.5" meanWaitTime="18.777045230330003" reqDropFraction="0.7455" waitTimeStddev="3.8280310358546714"/>
    <simulation meanReqArrivalRate="42.6" meanWaitTime="18.395321900100743" reqDropFraction="0.7359" waitTimeStddev="3.4882303891328976"/>
    <simulation meanReqArrivalRate="42.7" meanWaitTime="18.83167172884186" reqDropFraction="0.74" waitTimeStddev="3.68459065491844"/>
    <simulation meanReqArrivalRate="42.800000000000004" meanWaitTime="18.1061728842502" reqDropFraction="0.7359" waitTimeStddev="3.396077974355214"/>
    <simulation meanReqArrivalRate="42.900000000000006" meanWaitTime="17.800157436067263" reqDropFraction="0.7309" waitTimeStddev="3.4762029398580077"/>
    <simulation meanReqArrivalRate="43.0" meanWaitTime="18.543471522141388" reqDropFraction="0.7456" waitTimeStddev="3.479605460888963"/>
    <simulation meanReqArrivalRate="43.1" meanWaitTime="17.862213499912272" reqDropFraction="0.738" waitTimeStddev="3.3090272473817084"/>
    <simulation meanReqArrivalRate="43.2" meanWaitTime="18.13425525999566" reqDropFraction="0.7389" waitTimeStddev="3.505093780026707"/>
    <simulation meanReqArrivalRate="43.300000000000004" meanWaitTime="18.39086350654225" reqDropFraction="0.7422" waitTimeStddev="3.441801588050289"/>
    <simulation meanReqArrivalRate="43.400000000000006" meanWaitTime="19.069527614779155" reqDropFraction="0.7483" waitTimeStddev="3.7414673672111203"/>
    <simulation meanReqArrivalRate="43.5" meanWaitTime="18.14123972590433" reqDropFraction="0.7408" waitTimeStddev="3.4963445305765393"/>
    <simulation meanReqArrivalRate="43.6" meanWaitTime="18.052351018996276" reqDropFraction="0.7395" waitTimeStddev="3.4757772481790288"/>
    <simulation meanReqArrivalRate="43.7" meanWaitTime="17.875039868486866" reqDropFraction="0.7367" waitTimeStddev="3.8762320860338866"/>
    <simulation meanReqArrivalRate="43.800000000000004" meanWaitTime="18.50211046337051" reqDropFraction="0.747" waitTimeStddev="3.8687531926651357"/>
    <simulation meanReqArrivalRate="43.900000000000006" meanWaitTime="18.983781199414942" reqDropFraction="0.757" waitTimeStddev="4.285472054766697"/>
    <simulation meanReqArrivalRate="44.0" meanWaitTime="18.53774860968206" reqDropFraction="0.7439" waitTimeStddev="3.597835250589957"/>
    <simulation meanReqArrivalRate="44.1" meanWaitTime="18.117857348651512" reqDropFraction="0.7408" waitTimeStddev="3.5147682162709173"/>
    <simulation meanReqArrivalRate="44.2" meanWaitTime="17.728286012498565" reqDropFraction="0.7379" waitTimeStddev="3.339669459820731"/>
    <simulation meanReqArrivalRate="44.300000000000004" meanWaitTime="18.697800198130547" reqDropFraction="0.7566" waitTimeStddev="3.775023070999175"/>
    <simulation meanReqArrivalRate="44.400000000000006" meanWaitTime="18.094248330750602" reqDropFraction="0.7412" waitTimeStddev="3.421634371241176"/>
    <simulation meanReqArrivalRate="44.5" meanWaitTime="18.67400175891493" reqDropFraction="0.7523" waitTimeStddev="3.703725481474064"/>
    <simulation meanReqArrivalRate="44.6" meanWaitTime="19.547395023504386" reqDropFraction="0.769" waitTimeStddev="3.6855092263742333"/>
    <simulation meanReqArrivalRate="44.7" meanWaitTime="18.248208563349635" reqDropFraction="0.7427" waitTimeStddev="4.1926240679101765"/>
    <simulation meanReqArrivalRate="44.800000000000004" meanWaitTime="18.328836453419964" reqDropFraction="0.748" waitTimeStddev="3.6183256675299935"/>
    <simulation meanReqArrivalRate="44.900000000000006" meanWaitTime="18.593406818747802" reqDropFraction="0.7597" waitTimeStddev="3.8686151220752967"/>
    <simulation meanReqArrivalRate="45.0" meanWaitTime="18.186931122973604" reqDropFraction="0.7464" waitTimeStddev="3.8330447662053193"/>
    <simulation meanReqArrivalRate="45.1" meanWaitTime="17.996265295373657" reqDropFraction="0.7456" waitTimeStddev="3.535469155383271"/>
    <simulation meanReqArrivalRate="45.2" meanWaitTime="18.738094415833437" reqDropFraction="0.7552" waitTimeStddev="3.898764491163633"/>
    <simulation meanReqArrivalRate="45.300000000000004" meanWaitTime="17.77597091918194" reqDropFraction="0.7458" waitTimeStddev="3.3574911502837166"/>
    <simulation meanReqArrivalRate="45.400000000000006" meanWaitTime="18.636813539976796" reqDropFraction="0.7574" waitTimeStddev="3.6213734823803745"/>
    <simulation meanReqArrivalRate="45.5" meanWaitTime="18.67844053528227" reqDropFraction="0.7582" waitTimeStddev="3.592281704782274"/>
    <simulation meanReqArrivalRate="45.6" meanWaitTime="18.922403139542396" reqDropFraction="0.7599" waitTimeStddev="3.898870466733237"/>
    <simulation meanReqArrivalRate="45.7" meanWaitTime="18.24661593940612" reqDropFraction="0.7535" waitTimeStddev="3.8094295098319226"/>
    <simulation meanReqArrivalRate="45.800000000000004" meanWaitTime="19.510211886860787" reqDropFraction="0.7681" waitTimeStddev="4.248046160893041"/>
    <simulation meanReqArrivalRate="45.900000000000006" meanWaitTime="17.96800603418309" reqDropFraction="0.7521" waitTimeStddev="3.6935341608495262"/>
    <simulation meanReqArrivalRate="46.0" meanWaitTime="17.82275675315416" reqDropFraction="0.7444" waitTimeStddev="3.6302112223039384"/>
    <simulation meanReqArrivalRate="46.1" meanWaitTime="19.59194941024319" reqDropFraction="0.7704" waitTimeStddev="3.9142780899906087"/>
    <simulation meanReqArrivalRate="46.2" meanWaitTime="18.457745607553175" reqDropFraction="0.7616" waitTimeStddev="3.801768547681286"/>
    <simulation meanReqArrivalRate="46.300000000000004" meanWaitTime="18.24899123527736" reqDropFraction="0.7542" waitTimeStddev="4.190436767904742"/>
    <simulation meanReqArrivalRate="46.400000000000006" meanWaitTime="18.412123363925346" reqDropFraction="0.7569" waitTimeStddev="3.4711959410037054"/>
    <simulation meanReqArrivalRate="46.5" meanWaitTime="18.609465240473654" reqDropFraction="0.7615" waitTimeStddev="3.642242405873305"/>
    <simulation meanReqArrivalRate="46.6" meanWaitTime="18.432657381745734" reqDropFraction="0.7611" waitTimeStddev="3.532067275943377"/>
    <simulation meanReqArrivalRate="46.7" meanWaitTime="17.986528880800666" reqDropFraction="0.7553" waitTimeStddev="3.71764709477135"/>
    <simulation meanReqArrivalRate="46.800000000000004" meanWaitTime="18.22788774407282" reqDropFraction="0.7542" waitTimeStddev="3.9530373823646534"/>
    <simulation meanReqArrivalRate="46.900000000000006" meanWaitTime="18.91745634888375" reqDropFraction="0.7668" waitTimeStddev="3.687698204155824"/>
    <simulation meanReqArrivalRate="47.0" meanWaitTime="18.290382387427105" reqDropFraction="0.757" waitTimeStddev="3.9619031390133785"/>
    <simulation meanReqArrivalRate="47.1" meanWaitTime="18.68391367231129" reqDropFraction="0.7642" waitTimeStddev="3.460453187461276"/>
    <simulation meanReqArrivalRate="47.2" meanWaitTime="18.659097701387083" reqDropFraction="0.7618" waitTimeStddev="4.100614025798375"/>
    <simulation meanReqArrivalRate="47.300000000000004" meanWaitTime="18.636654925392552" reqDropFraction="0.762" waitTimeStddev="3.8582917747111747"/>
    <simulation meanReqArrivalRate="47.400000000000006" meanWaitTime="19.09782297489041" reqDropFraction="0.7711" waitTimeStddev="4.272352281237161"/>
    <simulation meanReqArrivalRate="47.5" meanWaitTime="19.053553525893506" reqDropFraction="0.7754" waitTimeStddev="4.371323807840807"/>
    <simulation meanReqArrivalRate="47.6" meanWaitTime="19.03135028367874" reqDropFraction="0.7772" waitTimeStddev="4.148529128172347"/>
    <simulation meanReqArrivalRate="47.7" meanWaitTime="18.843126763904007" reqDropFraction="0.7723" waitTimeStddev="4.197257257906826"/>
    <simulation meanReqArrivalRate="47.800000000000004" meanWaitTime="19.01310518222689" reqDropFraction="0.77" waitTimeStddev="3.6669023587602187"/>
    <simulation meanReqArrivalRate="47.900000000000006" meanWaitTime="18.404907097046234" reqDropFraction="0.7669" waitTimeStddev="3.495671155276831"/>
    <simulation meanReqArrivalRate="48.0" meanWaitTime="18.097435081551946" reqDropFraction="0.7641" waitTimeStddev="3.5532925840140974"/>
    <simulation meanReqArrivalRate="48.1" meanWaitTime="18.8636674859165" reqDropFraction="0.7763" waitTimeStddev="3.9669239766399067"/>
    <simulation meanReqArrivalRate="48.2" meanWaitTime="18.494380528708632" reqDropFraction="0.7706" waitTimeStddev="3.491307346098197"/>
    <simulation meanReqArrivalRate="48.300000000000004" meanWaitTime="18.092486627450505" reqDropFraction="0.7631" waitTimeStddev="3.5938338363280122"/>
    <simulation meanReqArrivalRate="48.400000000000006" meanWaitTime="18.454504840247385" reqDropFraction="0.7658" waitTimeStddev="3.5660523566221425"/>
    <simulation meanReqArrivalRate="48.5" meanWaitTime="18.764642296255943" reqDropFraction="0.7727" waitTimeStddev="3.6586970444002542"/>
    <simulation meanReqArrivalRate="48.6" meanWaitTime="17.965389056575933" reqDropFraction="0.7639" waitTimeStddev="3.292887491190135"/>
    <simulation meanReqArrivalRate="48.7" meanWaitTime="18.557087902925034" reqDropFraction="0.7756" waitTimeStddev="3.7045844442329274"/>
    <simulation meanReqArrivalRate="48.800000000000004" meanWaitTime="19.174358358872958" reqDropFraction="0.7735" waitTimeStddev="4.361928653049161"/>
    <simulation meanReqArrivalRate="48.900000000000006" meanWaitTime="18.58556153453665" reqDropFraction="0.7692" waitTimeStddev="3.6278326864229578"/>
    <simulation meanReqArrivalRate="49.0" meanWaitTime="18.319174613632107" reqDropFraction="0.7663" waitTimeStddev="3.28797890701705"/>
    <simulation meanReqArrivalRate="49.1" meanWaitTime="18.76982788266388" reqDropFraction="0.7732" waitTimeStddev="4.129031520039861"/>
    <simulation meanReqArrivalRate="49.2" meanWaitTime="18.090227019440434" reqDropFraction="0.7702" waitTimeStddev="3.8250202497249024"/>
    <simulation meanReqArrivalRate="49.300000000000004" meanWaitTime="17.655793204343226" reqDropFraction="0.7647" waitTimeStddev="3.7095837472794075"/>
    <simulation meanReqArrivalRate="49.400000000000006" meanWaitTime="19.033939578718112" reqDropFraction="0.7826" waitTimeStddev="4.135144792286672"/>
    <simulation meanReqArrivalRate="49.5" meanWaitTime="18.80191631895044" reqDropFraction="0.7759" waitTimeStddev="3.8048183133319537"/>
    <simulation meanReqArrivalRate="49.6" meanWaitTime="18.29818778506374" reqDropFraction="0.7714" waitTimeStddev="3.7376571874350675"/>
    <simulation meanReqArrivalRate="49.7" meanWaitTime="18.49787058059863" reqDropFraction="0.7749" waitTimeStddev="3.773289546369454"/>
    <simulation meanReqArrivalRate="49.800000000000004" meanWaitTime="18.367624860185977" reqDropFraction="0.7743" waitTimeStddev="3.783416766727247"/>
    <simulation meanReqArrivalRate="49.900000000000006" meanWaitTime="18.189905025463716" reqDropFraction="0.7802" waitTimeStddev="3.617989339284003"/>
    <simulation meanReqArrivalRate="50.0" meanWaitTime="18.528574412256372" reqDropFraction="0.7768" waitTimeStddev="3.6548071612033297"/>
  </simulations>
</swebserv>
